pdftk_remove_pages/__init__.py
pdftk_remove_pages/main.py
tests/__init__.py
tests/pdftk_remove_pages/__init__.py
tests/pdftk_remove_pages/test_main.py
pdftk_wrapper-0.0.4.dist-info/LICENSE
pdftk_wrapper-0.0.4.dist-info/METADATA
pdftk_wrapper-0.0.4.dist-info/WHEEL
pdftk_wrapper-0.0.4.dist-info/entry_points.txt
pdftk_wrapper-0.0.4.dist-info/top_level.txt
pdftk_wrapper-0.0.4.dist-info/RECORD
