Metadata-Version: 2.1
Name: pdftk-wrapper
Version: 0.0.4
Summary: A pdftk wrapper.
Author-email: Mmanu Chaturvedi <mmanu.chaturvedi@gmail.com>
Project-URL: Repository, https://github.com/m-chaturvedi/pdftk-wrapper
Requires-Python: >=3.8
License-File: LICENSE
